{
  "culture": "zh-Hans",
  "Texts": {
    "Menu:Home": "家园",
    "Welcome": "欢迎",
    "LongWelcomeMessage": "欢迎来到该应用系统，这是一个基于Abp框架的启动项目. 有关更多消息, 请访问 abp.io.",
    "Menu:BookStore": "图书馆",
    "BookStore": "图书馆管理",
    "Menu:Books": "书籍",
    "Actions": "活动",
    "Close": "关闭",
    "Delete": "删除",
    "Edit": "编辑",
    "PublishDate": "出版日期",
    "NewBook": "新书",
    "Name": "书名",
    "Type": "类型",
    "Price": "价格",
    "CreationTime": "创建时间",
    "AreYouSure": "你确定吗?",
    "AreYouSureToDelete": "是否确实要删除此项目?",
    "Enum:BookType.Undefined": "未定义",
    "Enum:BookType.Adventure": "冒险",
    "Enum:BookType.Biography": "传记",
    "Enum:BookType.Dystopia": "推想",
    "Enum:BookType.Fantastic": "幻想",
    "Enum:BookType.Horror": "恐怖",
    "Enum:BookType.Science": "科学",
    "Enum:BookType.ScienceFiction": "科幻",
    "Enum:BookType.Poetry": "诗",
    "BookDeletionConfirmationMessage": "您确定要删除'{0}'这本书吗??",
    "SuccessfullyDeleted": "成功删除!",
    "Permission:BookStore": "图书管",
    "Permission:Books": "图书",
    "Permission:Create": "创建",
    "Permission:Edit": "编辑",
    "Permission:Delete": "删除",
    "BookStore:00001": "已经有这样的作者了，名字是: {name}",
    "Permission:Authors": "作者",
    "Menu:Authors": "作者",
    "Authors": "作者",
    "AuthorDeletionConfirmationMessage": "你确定要删除作者 '{0}'吗?",
    "BirthDate": "出生日期",
    "NewAuthor": "新作者",
    "ShortBio": "个人简介"
  }
}